og_pilot/__init__.py
og_pilot/client.py
og_pilot/config.py
og_pilot/exceptions.py
og_pilot/jwt_encoder.py
og_pilot/django/__init__.py
og_pilot/django/apps.py
og_pilot/django/management/__init__.py
og_pilot/django/management/commands/__init__.py
og_pilot/django/management/commands/og_pilot_check.py
og_pilot/django/templates/og_pilot/meta_tags.html
og_pilot/django/templatetags/__init__.py
og_pilot/django/templatetags/og_pilot_tags.py
og_pilot-0.1.1.dist-info/METADATA
og_pilot-0.1.1.dist-info/WHEEL
og_pilot-0.1.1.dist-info/licenses/LICENSE
og_pilot-0.1.1.dist-info/RECORD
