Metadata-Version: 2.4
Name: og-pilot
Version: 0.1.1
Summary: Python client for the OG Pilot Open Graph image generator with Django integration
Project-URL: Homepage, https://ogpilot.com
Project-URL: Documentation, https://ogpilot.com/docs
Project-URL: Repository, https://github.com/sunergos-ro/og-pilot-python
Project-URL: Issues, https://github.com/sunergos-ro/og-pilot-python/issues
Project-URL: Changelog, https://github.com/sunergos-ro/og-pilot-python/commits/main
Author-email: Sunergos IT LLC <office@sunergos.ro>, Raul Popadineti <raul@sunergos.ro>
License-Expression: MIT
License-File: LICENSE
Keywords: django,meta-tags,og-image,og-pilot,open-graph,seo,social-media
Classifier: Development Status :: 4 - Beta
Classifier: Environment :: Web Environment
Classifier: Framework :: Django
Classifier: Framework :: Django :: 4.2
Classifier: Framework :: Django :: 5.0
Classifier: Framework :: Django :: 5.1
Classifier: Intended Audience :: Developers
Classifier: License :: OSI Approved :: MIT License
Classifier: Operating System :: OS Independent
Classifier: Programming Language :: Python :: 3
Classifier: Programming Language :: Python :: 3.10
Classifier: Programming Language :: Python :: 3.11
Classifier: Programming Language :: Python :: 3.12
Classifier: Programming Language :: Python :: 3.13
Classifier: Topic :: Internet :: WWW/HTTP
Classifier: Topic :: Software Development :: Libraries :: Python Modules
Requires-Python: >=3.10
Requires-Dist: pyjwt>=2.0.0
Requires-Dist: requests>=2.25.0
Provides-Extra: dev
Requires-Dist: django>=4.2; extra == 'dev'
Requires-Dist: mypy>=1.0; extra == 'dev'
Requires-Dist: pytest-cov>=4.0; extra == 'dev'
Requires-Dist: pytest>=7.0; extra == 'dev'
Requires-Dist: responses>=0.23.0; extra == 'dev'
Requires-Dist: ruff>=0.1.0; extra == 'dev'
Requires-Dist: types-requests>=2.31.0; extra == 'dev'
Provides-Extra: django
Requires-Dist: django>=4.2; extra == 'django'
